ArnorLib/ArnorLib.py
ArnorLib/Datastructures.py
ArnorLib/Datatypes.py
ArnorLib/GraphTheory.py
ArnorLib/SortingTools.py
ArnorLib/Wrappers.py
ArnorLib/__init__.py
ArnorLib-1.0.2.dist-info/LICENSE
ArnorLib-1.0.2.dist-info/METADATA
ArnorLib-1.0.2.dist-info/WHEEL
ArnorLib-1.0.2.dist-info/top_level.txt
ArnorLib-1.0.2.dist-info/RECORD
